{
  "settings": {
    "API_TOKEN": "224fdfc92a874a1069f53faf",
    "CUSTOM_REGEXPS": {
      "Basic (type in the answer)": "",
      "Basic": "((?:[^\\n][\\n]?)+\\n)---((?:\\n(?:^.{1,3}$|^.{4}(?<!<!--).*))*)",
      "DRAW": "",
      "Cloze (overlapping)": "",
      "Basic (and reversed card)": ""
    },
    "FILE_LINK_FIELDS": {
      "Basic (type in the answer)": "Front",
      "Basic": "Front",
      "DRAW": "DRAW",
      "Cloze (overlapping)": "Text15",
      "Basic (and reversed card)": "Front"
    },
    "CONTEXT_FIELDS": {},
    "FOLDER_DECKS": {
      "templater": ""
    },
    "FOLDER_TAGS": {
      "templater": ""
    },
    "Syntax": {
      "Begin Card": "START",
      "End Card": "END",
      "Begin Inline Card": "STARTI",
      "End Inline Card": "ENDI",
      "Target Deck Line": "TARGET DECK",
      "File Tags Line": "FILE TAGS",
      "Delete Card Line": "DELETE",
      "Frozen Fields Line": "FROZEN"
    },
    "Defaults": {
      "Tag": "obsidian-to-mochi",
      "DeckName": "Default",
      "Scheduling Interval": 0,
      "Add File Link": false,
      "Add Context": false,
      "CurlyCloze": false,
      "CurlyCloze - Highlights to Clozes": false,
      "ID Comments": true,
      "Add Obsidian Tags": false
    }
  },
  "card_hashes_by_id": {},
  "persisted_attachment_links_by_id": {},
  "field_names_by_template_name": {
    "Basic (type in the answer)": [
      "Front",
      "Back"
    ],
    "Basic": [
      "Front",
      "Back"
    ],
    "DRAW": [
      "DRAW",
      "Q"
    ],
    "Cloze (overlapping)": [
      "Text15",
      "Text13",
      "Sources",
      "Settings",
      "Title",
      "Text1",
      "Text18",
      "Text5",
      "Text10",
      "Original",
      "Text14",
      "Remarks",
      "Text9",
      "Text16",
      "Text2",
      "Text8",
      "Text6",
      "Text19",
      "Text20",
      "Text17",
      "Text3",
      "Text7",
      "Text11",
      "Text4",
      "Text12",
      "Full"
    ],
    "Basic (and reversed card)": [
      "Front",
      "Back"
    ]
  },
  "file_hashes_by_path": {}
}